flinx/__init__.py
flinx/commands.py
flinx/configuration.py
flinx/extensions.py
flinx/generation.py
flinx/project_metadata.py
flinx/templates/conf.py.tpl
flinx/templates/index.rst.tpl
flinx-0.2.0.dist-info/entry_points.txt
flinx-0.2.0.dist-info/LICENSE
flinx-0.2.0.dist-info/WHEEL
flinx-0.2.0.dist-info/METADATA
flinx-0.2.0.dist-info/RECORD
