Metadata-Version: 2.1
Name: flinx
Version: 0.2.0
Summary: Configuration-free Python doc generation via Sphinx.
Home-page: https://github.com/osteele/flinx
License: UNKNOWN
Author: Oliver Steele
Author-email: steele@osteele.com
Requires-Python: >=3.5
Classifier: Environment :: Console
Classifier: License :: OSI Approved :: MIT License
Classifier: Operating System :: OS Independent
Classifier: Programming Language :: Python
Classifier: Programming Language :: Python :: 3.6
Classifier: Topic :: Documentation
Classifier: Topic :: Documentation :: Sphinx
Classifier: Topic :: Software Development :: Documentation
Requires-Dist: click
Requires-Dist: flit
Requires-Dist: Sphinx
Requires-Dist: sphinx-autobuild
Project-URL: Documentation, https://flinx.readthedocs.io/en/latest/
